{
  "contentVersion": "1.0.0",
  "storyFile": "story.md",
  "title": "歌と仕事",
  "englishTitle": "Song and Work",
  "terms": {

    "りきぞ": { "id": "char_rikizo", "form": null },
    "ミキ": { "id": "char_miki", "form": null },

    "は": { "id": "p_wa", "form": null },
    "が": { "id": "p_ga", "form": null },
    "を": { "id": "p_wo", "form": null },
    "の": { "id": "p_no", "form": null },
    "に": { "id": "p_ni", "form": null },
    "で": { "id": "p_de", "form": null },
    "も": { "id": "p_mo", "form": null },
    "と": { "id": "p_to_quote", "form": null },
    "から": { "id": "p_kara_because", "form": null },
    "か": { "id": "p_ka", "form": null },
    "だけ": { "id": "p_dake", "form": null },
    "しか": { "id": "p_shika", "form": null },
    "です": { "id": "g_desu", "form": null },
    "でした": { "id": "g_desu", "form": null },

    "会社員": { "id": "v_kaishain", "form": null },
    "毎日": { "id": "v_mainichi", "form": null },
    "早起き": { "id": "v_hayaoki", "form": null },
    "会社": { "id": "v_kaisha", "form": null },
    "仕事": { "id": "v_shigoto", "form": null },
    "いそがしくて": { "id": "v_isogashii", "form": "te_form" },
    "長い": { "id": "v_nagai", "form": null },
    "一日": { "id": "v_ichinichi", "form": null },
    "昼ご飯": { "id": "v_hirugohan", "form": null },
    "時": { "id": "v_toki", "form": null },
    "音楽": { "id": "v_ongaku", "form": null },
    "心": { "id": "v_kokoro", "form": null },
    "ある": { "id": "v_aru", "form": null },
    "とても": { "id": "v_totemo", "form": null },
    "その": { "id": "v_sono", "form": null },
    "学校": { "id": "v_gakkou", "form": null },

    "木曜日": { "id": "v_mokuyoubi", "form": null },
    "早く": { "id": "v_hayai", "form": "adverbial" },
    "町": { "id": "v_machi", "form": null },
    "小さい": { "id": "v_chiisai", "form": null },
    "店": { "id": "v_mise", "form": null },
    "所": { "id": "v_tokoro", "form": null },
    "電車": { "id": "v_densha", "form": null },

    "一人": { "id": "v_hitori", "form": null },
    "歌手": { "id": "v_kashu", "form": null },
    "声": { "id": "v_koe", "form": null },
    "低くて": { "id": "v_hikui", "form": "te_form" },
    "楽しかったです": { "id": "v_tanoshii", "form": "polite_past_adj" },
    "軽い": { "id": "v_karui", "form": null },
    "楽しく": { "id": "v_tanoshii", "form": "adverbial" },

    "後": { "id": "v_ato", "form": null },
    "私": { "id": "v_watashi", "form": null },
    "週まつ": { "id": "v_shuumatsu", "form": null },
    "いいえ": { "id": "v_iie", "form": null },
    "さん": { "id": "v_san", "form": null },
    "好きです": { "id": "v_suki", "form": "polite_adj" },

    "どうして": { "id": "v_doushite", "form": null },
    "大切な": { "id": "v_taisetsu", "form": "attributive_na" },
    "こと": { "id": "v_koto", "form": null },
    "帰り道": { "id": "v_kaerimichi", "form": null },
    "中": { "id": "v_naka", "form": null },
    "明日": { "id": "v_ashita", "form": null },
    "金曜日": { "id": "v_kinyoubi", "form": null },
    "歌": { "id": "v_uta", "form": null },
    "音": { "id": "v_oto", "form": null },

    "して": { "id": "v_suru", "form": "te_form" },
    "します": { "id": "v_suru", "form": "polite_masu" },
    "しました": { "id": "v_suru", "form": "polite_mashita" },
    "急ぎました": { "id": "v_isogu", "form": "polite_mashita" },
    "聞きました": { "id": "v_kiku", "form": "polite_mashita" },
    "聞いて": { "id": "v_kiku", "form": "te_form" },
    "いる": { "id": "v_iru", "form": "plain_form" },
    "いました": { "id": "v_iru", "form": "polite_mashita" },
    "軽く": { "id": "v_karui", "form": "adverbial" },
    "なりました": { "id": "v_naru", "form": "polite_mashita" },
    "なります": { "id": "v_naru", "form": "polite_masu" },

    "終わりました": { "id": "v_owaru", "form": "polite_mashita" },
    "行く": { "id": "v_iku", "form": "plain_form" },
    "行きたかった": { "id": "v_iku", "form": "plain_desire_tai_past" },
    "出て": { "id": "v_deru", "form": "te_form" },
    "乗りました": { "id": "v_noru", "form": "polite_mashita" },

    "入った": { "id": "v_hairu", "form": "plain_past" },
    "歌って": { "id": "v_utau", "form": "te_form" },
    "立って": { "id": "v_tatsu", "form": "te_form" },

    "終わった": { "id": "v_owaru", "form": "plain_past" },
    "言いました": { "id": "v_iu", "form": "polite_mashita" },
    "歌う": { "id": "v_utau", "form": "plain_form" },
    "歌います": { "id": "v_utau", "form": "polite_masu" },
    "歌いません": { "id": "v_utau", "form": "polite_negative" },
    "聞きながら": { "id": "v_kiku", "form": "nagara_form" },

    "分かりました": { "id": "v_wakaru", "form": "polite_mashita" },
    "ありました": { "id": "v_aru", "form": "polite_mashita" }
  }
}
