{
  "contentVersion": "1.0.0",
  "id": "N4.30",
  "title": "Thinking, Gathering & Answering",
  "meta": {
    "level": "N4",
    "lesson_number": 30,
    "focus": "Thoughts, memories, and gatherings — expressing opinions with と思う, recalling with 思い出す, collecting or answering in everyday contexts",
    "estimated_minutes": 35,
    "kanji": [
      "思",
      "特",
      "集",
      "答"
    ]
  },
  "newKanji": [
    {
      "kanji": "思",
      "on": "し",
      "kun": "おも",
      "meaning": "Think",
      "termId": "k_omou"
    },
    {
      "kanji": "特",
      "on": "とく",
      "kun": "",
      "meaning": "Special",
      "termId": "k_toku"
    },
    {
      "kanji": "集",
      "on": "しゅう",
      "kun": "あつ",
      "meaning": "Gather",
      "termId": "k_atsumeru"
    },
    {
      "kanji": "答",
      "on": "とう",
      "kun": "こた",
      "meaning": "Answer",
      "termId": "k_kotaeru"
    }
  ],
  "sections": [
    {
      "type": "warmup",
      "title": "Warm-Up Review（ウォームアップ）",
      "instructions": "Use words you already know to answer these questions:",
      "items": [
        {
          "jp": "毎日 勉強して、漢字が 読めるように なりました。",
          "en": "By studying every day, I came to be able to read kanji.",
          "terms": [
            "v_mainichi",
            "v_benkyou",
            {
              "id": "v_suru",
              "form": "te_form"
            },
            "v_kanji",
            "p_ga",
            {
              "id": "v_yomu",
              "form": "potential"
            },
            "v_you_manner",
            "p_ni",
            {
              "id": "v_naru",
              "form": "polite_mashita"
            }
          ]
        },
        {
          "jp": "仕事が 終わったら、友だちに 電話します。",
          "en": "When work is done, I'll call my friend.",
          "terms": [
            "v_shigoto",
            "p_ga",
            {
              "id": "v_owaru",
              "form": "conditional_tara"
            },
            "v_tomodachi",
            "p_ni",
            "v_denwa",
            {
              "id": "v_suru",
              "form": "polite_masu"
            }
          ]
        },
        {
          "jp": "週まつは 音楽を 聞いたり、映画を 見たり します。",
          "en": "On weekends, I listen to music, watch movies, and things like that.",
          "terms": [
            "v_shuumatsu",
            "p_wa",
            "v_ongaku",
            "p_wo",
            {
              "id": "v_kiku",
              "form": "tari_form"
            },
            "v_eiga",
            "p_wo",
            {
              "id": "v_miru",
              "form": "tari_form"
            },
            {
              "id": "v_suru",
              "form": "polite_masu"
            }
          ]
        },
        {
          "jp": "試験の 前に、よく 読まなければ いけません。",
          "en": "You have to read carefully before the exam.",
          "terms": [
            "v_shiken",
            "p_no",
            "v_mae",
            "p_ni",
            "v_yoku",
            {
              "id": "v_yomu",
              "form": "nakereba"
            },
            {
              "id": "v_ikeru",
              "form": "polite_negative"
            }
          ]
        }
      ]
    },
    {
      "type": "kanjiGrid",
      "title": "New Kanji（新しい 漢字）",
      "items": [
        {
          "kanji": "思",
          "on": "し",
          "kun": "おも",
          "meaning": "Think",
          "words": [
            "k_omou",
            "v_omou",
            "v_omoi_feel",
            "v_omoidasu",
            "v_omoide",
            "v_omoiagaru",
            "v_ishi"
          ]
        },
        {
          "kanji": "特",
          "on": "とく",
          "kun": "",
          "meaning": "Special",
          "words": [
            "k_toku",
            "v_tokubetsu",
            "v_tokuni",
            "v_tokkyuu",
            "v_tokushuu"
          ]
        },
        {
          "kanji": "集",
          "on": "しゅう",
          "kun": "あつ",
          "meaning": "Gather",
          "words": [
            "k_atsumeru",
            "v_atsumeru",
            "v_atsumaru",
            "v_shuuchuu",
            "v_shuukai",
            "v_bunshuu",
            "v_shuu"
          ]
        },
        {
          "kanji": "答",
          "on": "とう",
          "kun": "こた",
          "meaning": "Answer",
          "words": [
            "k_kotaeru",
            "v_kotae",
            "v_kotaeru",
            "v_mondou",
            "v_kuchigotae"
          ]
        }
      ]
    },
    {
      "type": "vocabList",
      "title": "Vocabulary & Compounds（ことば）",
      "groups": [
        {
          "label": "Thinking & Feeling",
          "items": [
            "v_omou",
            "v_omoi_feel",
            "v_omoidasu",
            "v_omoide",
            "v_omoiagaru",
            "v_ishi"
          ]
        },
        {
          "label": "Special Things",
          "items": [
            "v_tokubetsu",
            "v_tokuni",
            "v_tokkyuu",
            "v_tokushuu"
          ]
        },
        {
          "label": "Gathering & Meeting",
          "items": [
            "v_atsumeru",
            "v_atsumaru",
            "v_shuuchuu",
            "v_shuukai",
            "v_bunshuu",
            "v_shuu"
          ]
        },
        {
          "label": "Questions & Answers",
          "items": [
            "v_kotae",
            "v_kotaeru",
            "v_mondou",
            "v_kuchigotae"
          ]
        }
      ]
    },
    {
      "type": "conversation",
      "title": "Conversation 1: A Special Gathering",
      "context": "Two office colleagues discussing an upcoming company event.",
      "lines": [
        {
          "spk": "A",
          "jp": "来週、会社で 特別な 集会が あるんですよ。",
          "en": "There's a special company gathering next week.",
          "terms": [
            "v_raishuu",
            "v_kaisha",
            "p_de",
            {
              "id": "v_tokubetsu",
              "form": "attributive_na"
            },
            "v_shuukai",
            "p_ga",
            {
              "id": "v_aru",
              "form": "plain_form"
            },
            "p_ndesu",
            "p_yo"
          ]
        },
        {
          "spk": "B",
          "jp": "楽しそうですね！この 会社の 集会に 行ったことが ありますか。",
          "en": "Sounds wonderful! Have you been to this company's gatherings before?",
          "terms": [
            {
              "id": "v_tanoshii",
              "form": "appearance_sou"
            },
            "p_ne",
            "v_kono",
            "v_kaisha",
            "p_no",
            "v_shuukai",
            "p_ni",
            {
              "id": "v_iku",
              "form": "plain_past"
            },
            "v_koto",
            "p_ga",
            {
              "id": "v_aru",
              "form": "polite_masu"
            },
            "p_ka"
          ]
        },
        {
          "spk": "A",
          "jp": "はい。去年より 多く 集まると 思います。特に 大切な ことが あるんです。",
          "en": "Yes. I think more will gather than last year. There's something especially important.",
          "terms": [
            "p_hai",
            "v_kyonen",
            "p_yori",
            {
              "id": "v_ooi",
              "form": "adverbial"
            },
            {
              "id": "v_atsumaru",
              "form": "plain_form"
            },
            "p_to_quote",
            {
              "id": "v_omou",
              "form": "polite_masu"
            },
            "v_tokuni",
            {
              "id": "v_taisetsu",
              "form": "attributive_na"
            },
            "v_koto",
            "p_ga",
            {
              "id": "v_aru",
              "form": "plain_form"
            },
            "p_ndesu"
          ]
        },
        {
          "spk": "B",
          "jp": "それは 楽しいですね。いっしょに 行きましょう。",
          "en": "That sounds great! Let's go together.",
          "terms": [
            "v_sore",
            "p_wa",
            {
              "id": "v_tanoshii",
              "form": "polite_adj"
            },
            "p_ne",
            "v_issho",
            {
              "id": "v_iku",
              "form": "polite_volitional_mashou"
            }
          ]
        }
      ]
    },
    {
      "type": "conversation",
      "title": "Conversation 2: The Class Anthology",
      "context": "A student tells a classmate about the class writing anthology project.",
      "lines": [
        {
          "spk": "A",
          "jp": "クラス の 文集に どんな ことを 書きますか。",
          "en": "What kinds of things will you write in the class anthology?",
          "terms": [
            "v_kurasu_class",
            "p_no",
            "v_bunshuu",
            "p_ni",
            "v_donna",
            "v_koto",
            "p_wo",
            {
              "id": "v_kaku",
              "form": "polite_masu"
            },
            "p_ka"
          ]
        },
        {
          "spk": "B",
          "jp": "先生に 思いを 書きたいと 思います。よく 集中して 書きます。",
          "en": "I'm thinking I'd like to write my feelings to my teacher. I'll concentrate and write.",
          "terms": [
            "v_sensei",
            "p_ni",
            "v_omoi_feel",
            "p_wo",
            {
              "id": "v_kaku",
              "form": "plain_desire_tai"
            },
            "p_to_quote",
            {
              "id": "v_omou",
              "form": "polite_masu"
            },
            "v_yoku",
            "v_shuuchuu",
            {
              "id": "v_suru",
              "form": "te_form"
            },
            {
              "id": "v_kaku",
              "form": "polite_masu"
            }
          ]
        },
        {
          "spk": "A",
          "jp": "いい 思いを 書きましたね。でも、思い上がらない ように しましょう。問答 しながら 考えると もっと いいですよ。",
          "en": "You wrote nice feelings. But let's be careful not to get conceited. It's even better to think while doing Q&A.",
          "terms": [
            "v_ii",
            "v_omoi_feel",
            "p_wo",
            {
              "id": "v_kaku",
              "form": "polite_mashita"
            },
            "p_ne",
            "p_demo_but",
            {
              "id": "v_omoiagaru",
              "form": "plain_negative"
            },
            "v_you_manner",
            "p_ni",
            {
              "id": "v_suru",
              "form": "polite_volitional_mashou"
            },
            "v_mondou",
            {
              "id": "v_suru",
              "form": "nagara_form"
            },
            {
              "id": "v_kangaeru",
              "form": "plain_form"
            },
            "p_to_conditional",
            "v_motto",
            {
              "id": "v_ii",
              "form": "polite_adj"
            },
            "p_yo"
          ]
        },
        {
          "spk": "B",
          "jp": "そうですね。集中しなければ いけませんね。",
          "en": "You're right. I have to concentrate.",
          "terms": [
            "p_soudesu",
            "p_ne",
            "v_shuuchuu",
            {
              "id": "v_suru",
              "form": "nakereba"
            },
            {
              "id": "v_ikeru",
              "form": "polite_negative"
            },
            "p_ne"
          ]
        }
      ]
    },
    {
      "type": "conversation",
      "title": "Conversation 3: Looking at Old Photos (Casual)",
      "context": "Two close friends flip through a photo album together.",
      "lines": [
        {
          "spk": "A",
          "jp": "この 写真、見たことがある？",
          "en": "Have you seen this photo before?",
          "terms": [
            "v_kono",
            "v_shashin",
            {
              "id": "v_miru",
              "form": "plain_past"
            },
            "v_koto",
            "p_ga",
            {
              "id": "v_aru",
              "form": "plain_form"
            },
            "p_ka"
          ]
        },
        {
          "spk": "B",
          "jp": "うん、思い出した！特別な 旅行の 写真だよ。",
          "en": "Yeah, I remembered! It's a photo from a special trip.",
          "terms": [
            "v_un",
            {
              "id": "v_omoidasu",
              "form": "plain_past"
            },
            {
              "id": "v_tokubetsu",
              "form": "attributive_na"
            },
            "v_ryokou",
            "p_no",
            "v_shashin",
            "p_yo",
            "g_da"
          ]
        },
        {
          "spk": "A",
          "jp": "みんなで 集まって、とても 楽しかった よ ね。この 思い出は 特に 大切 だ と 思う。",
          "en": "We all gathered and it was so fun. I think this memory is especially precious.",
          "terms": [
            "v_minna",
            "p_de",
            {
              "id": "v_atsumaru",
              "form": "te_form"
            },
            "v_totemo",
            {
              "id": "v_tanoshii",
              "form": "plain_past_adj"
            },
            "p_yo",
            "p_ne",
            "v_kono",
            "v_omoide",
            "p_wa",
            "v_tokuni",
            "v_taisetsu",
            "g_da",
            "p_to_quote",
            {
              "id": "v_omou",
              "form": "plain_form"
            }
          ]
        },
        {
          "spk": "B",
          "jp": "うん。また みんなで 集まりたいな。",
          "en": "Yeah. I want to gather with everyone again.",
          "terms": [
            "v_un",
            "v_mata",
            "v_minna",
            "p_de",
            {
              "id": "v_atsumaru",
              "form": "plain_desire_tai"
            },
            "p_na"
          ]
        }
      ]
    },
    {
      "type": "conversation",
      "title": "Conversation 4: The Collection (Casual)",
      "context": "Two siblings at home talking about a stamp collection.",
      "lines": [
        {
          "spk": "A",
          "jp": "これ、切手の 特集 だね。いつから 集めているの？",
          "en": "This is a stamp special collection, right. Since when have you been collecting?",
          "terms": [
            "v_kore",
            "v_kitte",
            "p_no",
            "v_tokushuu",
            "p_ne",
            "g_da",
            "v_itsu",
            "p_kara",
            {
              "id": "v_atsumeru",
              "form": "te_form"
            },
            {
              "id": "v_iru",
              "form": "plain_form"
            },
            "p_no_question",
            "p_ka"
          ]
        },
        {
          "spk": "B",
          "jp": "前から 集めているよ。特に 古い 切手と 特急の 切手が 好きなんだ。",
          "en": "I've been collecting for a while. I especially like old stamps and express train stamps.",
          "terms": [
            "v_mae",
            "p_kara",
            {
              "id": "v_atsumeru",
              "form": "te_form"
            },
            {
              "id": "v_iru",
              "form": "plain_form"
            },
            "p_yo",
            "v_tokuni",
            "v_furui",
            "v_kitte",
            "p_to",
            "v_tokkyuu",
            "p_no",
            "v_kitte",
            "p_ga",
            {
              "id": "v_suki",
              "form": "attributive_na"
            },
            "p_nda"
          ]
        },
        {
          "spk": "A",
          "jp": "いくつ 集めたの？",
          "en": "How many have you collected?",
          "terms": [
            "v_ikutsu",
            {
              "id": "v_atsumeru",
              "form": "plain_past"
            },
            "p_no_question",
            "p_ka"
          ]
        },
        {
          "spk": "B",
          "jp": "学校や 図書館に 行ったり、友だちに 聞いたり して、百 ぐらい 集めてきたよ。",
          "en": "I went to school and libraries, asked friends, and things like that — I've collected about a hundred.",
          "terms": [
            "v_gakkou",
            "p_ya",
            "v_toshokan",
            "p_ni",
            {
              "id": "v_iku",
              "form": "tari_form"
            },
            "v_tomodachi",
            "p_ni",
            {
              "id": "v_kiku",
              "form": "tari_form"
            },
            {
              "id": "v_suru",
              "form": "te_form"
            },
            "v_hyaku",
            "p_kurai",
            {
              "id": "v_atsumeru",
              "form": "te_form"
            },
            {
              "id": "v_kuru",
              "form": "plain_past"
            },
            "p_yo"
          ]
        }
      ]
    },
    {
      "type": "reading",
      "title": "Reading Practice 1: The Town Gathering",
      "passage": [
        {
          "jp": "先週の 土曜日に、町で 特別な 集会が ありました。",
          "en": "Last Saturday, there was a special gathering in town.",
          "terms": [
            "v_senshuu",
            "p_no",
            "v_doyoubi",
            "p_ni",
            "v_machi",
            "p_de",
            {
              "id": "v_tokubetsu",
              "form": "attributive_na"
            },
            "v_shuukai",
            "p_ga",
            {
              "id": "v_aru",
              "form": "polite_mashita"
            }
          ]
        },
        {
          "jp": "学生や 会社員が たくさん 集まって、大切な ことを 話しました。",
          "en": "Many students and company employees gathered and talked about important matters.",
          "terms": [
            "v_gakusei",
            "p_ya",
            "v_kaishain",
            "p_ga",
            "v_takusan",
            {
              "id": "v_atsumaru",
              "form": "te_form"
            },
            {
              "id": "v_taisetsu",
              "form": "attributive_na"
            },
            "v_koto",
            "p_wo",
            {
              "id": "v_hanasu",
              "form": "polite_mashita"
            }
          ]
        },
        {
          "jp": "私も 写真 集を 作ったり、みんなの 答えを 集めたり しました。",
          "en": "I also made a photo collection, gathered everyone's answers, and things like that.",
          "terms": [
            "v_watashi",
            "p_mo",
            "v_shashin",
            "v_shuu",
            "p_wo",
            {
              "id": "v_tsukuru",
              "form": "tari_form"
            },
            "v_minna",
            "p_no",
            "v_kotae",
            "p_wo",
            {
              "id": "v_atsumeru",
              "form": "tari_form"
            },
            {
              "id": "v_suru",
              "form": "polite_mashita"
            }
          ]
        },
        {
          "jp": "特に、去年より 多く の 人が 集まって きました。",
          "en": "In particular, more people came and gathered than last year.",
          "terms": [
            "v_tokuni",
            "v_kyonen",
            "p_yori",
            {
              "id": "v_ooi",
              "form": "adverbial"
            },
            "p_no",
            "v_hito",
            "p_ga",
            {
              "id": "v_atsumaru",
              "form": "te_form"
            },
            {
              "id": "v_kuru",
              "form": "polite_mashita"
            }
          ]
        },
        {
          "jp": "来年も 集まれると いいと 思います。",
          "en": "I hope we'll be able to gather again next year.",
          "terms": [
            "v_rainen",
            "p_mo",
            {
              "id": "v_atsumaru",
              "form": "potential"
            },
            "p_to_conditional",
            "v_ii",
            "p_to_quote",
            {
              "id": "v_omou",
              "form": "polite_masu"
            }
          ]
        }
      ],
      "questions": [
        {
          "q": "集会は いつ ありましたか。",
          "q_en": "When was the gathering held?",
          "a": "先週の 土曜日に ありました。",
          "a_en": "It was held last Saturday.",
          "terms": [
            "v_shuukai",
            "p_wa",
            "v_itsu",
            {
              "id": "v_aru",
              "form": "polite_mashita"
            },
            "p_ka"
          ],
          "a_terms": [
            "v_senshuu",
            "p_no",
            "v_doyoubi",
            "p_ni",
            {
              "id": "v_aru",
              "form": "polite_mashita"
            }
          ]
        },
        {
          "q": "どんな 人が 集まりましたか。",
          "q_en": "What kind of people gathered?",
          "a": "学生や 会社員が 集まりました。",
          "a_en": "Students and company employees gathered.",
          "terms": [
            "v_donna",
            "v_hito",
            "p_ga",
            {
              "id": "v_atsumaru",
              "form": "polite_mashita"
            },
            "p_ka"
          ],
          "a_terms": [
            "v_gakusei",
            "p_ya",
            "v_kaishain",
            "p_ga",
            {
              "id": "v_atsumaru",
              "form": "polite_mashita"
            }
          ]
        },
        {
          "q": "「私」は 来年 どうなると いいと 思っていますか。",
          "q_en": "What does the narrator think would be good for next year?",
          "a": "また 集まれると いいと 思っています。",
          "a_en": "They think it would be good if people could gather again.",
          "terms": [
            "v_watashi",
            "p_wa",
            "v_rainen",
            "v_dou",
            {
              "id": "v_naru",
              "form": "plain_form"
            },
            "p_to_conditional",
            "v_ii",
            "p_to_quote",
            {
              "id": "v_omou",
              "form": "te_form"
            },
            {
              "id": "v_iru",
              "form": "polite_masu"
            },
            "p_ka"
          ],
          "a_terms": [
            "v_mata",
            {
              "id": "v_atsumaru",
              "form": "potential"
            },
            "p_to_conditional",
            "v_ii",
            "p_to_quote",
            {
              "id": "v_omou",
              "form": "te_form"
            },
            {
              "id": "v_iru",
              "form": "polite_masu"
            }
          ]
        }
      ]
    },
    {
      "type": "reading",
      "title": "Reading Practice 2: Concentrating and Answering",
      "passage": [
        {
          "jp": "先週、漢字の 試験が ありました。",
          "en": "Last week there was a kanji exam.",
          "terms": [
            "v_senshuu",
            "v_kanji",
            "p_no",
            "v_shiken",
            "p_ga",
            {
              "id": "v_aru",
              "form": "polite_mashita"
            }
          ]
        },
        {
          "jp": "学生は 試験の 前に 集中して 勉強しました。",
          "en": "The student concentrated and studied before the exam.",
          "terms": [
            "v_gakusei",
            "p_wa",
            "v_shiken",
            "p_no",
            "v_mae",
            "p_ni",
            "v_shuuchuu",
            {
              "id": "v_suru",
              "form": "te_form"
            },
            "v_benkyou",
            {
              "id": "v_suru",
              "form": "polite_mashita"
            }
          ]
        },
        {
          "jp": "でも、むずかしい 問題の 答えを 思い出す ことが できませんでした。",
          "en": "But the student could not recall the answer to a difficult question.",
          "terms": [
            "p_demo_but",
            "v_muzukashii",
            "v_mondai",
            "p_no",
            "v_kotae",
            "p_wo",
            {
              "id": "v_omoidasu",
              "form": "plain_form"
            },
            "v_koto",
            "p_ga",
            {
              "id": "v_dekiru",
              "form": "polite_past_negative"
            }
          ]
        },
        {
          "jp": "答えを 集めてから、また 考えるように しました。",
          "en": "After gathering answers, the student made an effort to think again.",
          "terms": [
            "v_kotae",
            "p_wo",
            {
              "id": "v_atsumeru",
              "form": "te_form"
            },
            "p_tekara",
            "v_mata",
            {
              "id": "v_kangaeru",
              "form": "plain_form"
            },
            "v_you_manner",
            "p_ni",
            {
              "id": "v_suru",
              "form": "polite_mashita"
            }
          ]
        },
        {
          "jp": "学生は 「分かりません」と 答えて、口答えは しませんでした。",
          "en": "The student answered \"I don't know\" and did not talk back.",
          "terms": [
            "v_gakusei",
            "p_wa",
            {
              "id": "v_wakaru",
              "form": "polite_negative"
            },
            "p_to_quote",
            {
              "id": "v_kotaeru",
              "form": "te_form"
            },
            "v_kuchigotae",
            "p_wa",
            {
              "id": "v_suru",
              "form": "polite_past_negative"
            }
          ]
        }
      ],
      "questions": [
        {
          "q": "学生は 試験の 前に 何を しましたか。",
          "q_en": "What did the student do before the exam?",
          "a": "集中して 勉強しました。",
          "a_en": "They concentrated and studied.",
          "terms": [
            "v_gakusei",
            "p_wa",
            "v_shiken",
            "p_no",
            "v_mae",
            "p_ni",
            "v_nani",
            "p_wo",
            {
              "id": "v_suru",
              "form": "polite_mashita"
            },
            "p_ka"
          ],
          "a_terms": [
            "v_shuuchuu",
            {
              "id": "v_suru",
              "form": "te_form"
            },
            "v_benkyou",
            {
              "id": "v_suru",
              "form": "polite_mashita"
            }
          ]
        },
        {
          "q": "学生は 答えを 思い出す ことが できましたか。",
          "q_en": "Could the student remember the answer?",
          "a": "いいえ、思い出す ことが できませんでした。",
          "a_en": "No, they could not remember it.",
          "terms": [
            "v_gakusei",
            "p_wa",
            "v_kotae",
            "p_wo",
            {
              "id": "v_omoidasu",
              "form": "plain_form"
            },
            "v_koto",
            "p_ga",
            {
              "id": "v_dekiru",
              "form": "polite_mashita"
            },
            "p_ka"
          ],
          "a_terms": [
            "v_iie",
            {
              "id": "v_omoidasu",
              "form": "plain_form"
            },
            "v_koto",
            "p_ga",
            {
              "id": "v_dekiru",
              "form": "polite_past_negative"
            }
          ]
        },
        {
          "q": "学生は 口答えを しましたか。",
          "q_en": "Did the student talk back?",
          "a": "いいえ、口答えは しませんでした。",
          "a_en": "No, they did not talk back.",
          "terms": [
            "v_gakusei",
            "p_wa",
            "v_kuchigotae",
            "p_wo",
            {
              "id": "v_suru",
              "form": "polite_mashita"
            },
            "p_ka"
          ],
          "a_terms": [
            "v_iie",
            "v_kuchigotae",
            "p_wa",
            {
              "id": "v_suru",
              "form": "polite_past_negative"
            }
          ]
        }
      ]
    },
    {
      "type": "drills",
      "title": "Drill 1: Kanji Readings",
      "instructions": "Choose the correct reading for each kanji.",
      "items": [
        {
          "kind": "mcq",
          "q": "思う の よみかたは？",
          "choices": [
            "おもう",
            "こたえる",
            "あつめる",
            "くわえる"
          ],
          "answer": "おもう"
        },
        {
          "kind": "mcq",
          "q": "特別 の よみかたは？",
          "choices": [
            "とくべつ",
            "とくに",
            "とっきゅう",
            "とくしゅう"
          ],
          "answer": "とくべつ"
        },
        {
          "kind": "mcq",
          "q": "集まる の よみかたは？",
          "choices": [
            "あつまる",
            "あつめる",
            "はじまる",
            "すすむ"
          ],
          "answer": "あつまる"
        },
        {
          "kind": "mcq",
          "q": "答える の よみかたは？",
          "choices": [
            "こたえる",
            "おもいだす",
            "かんがえる",
            "おしえる"
          ],
          "answer": "こたえる"
        },
        {
          "kind": "mcq",
          "q": "特急 の よみかたは？",
          "choices": [
            "とっきゅう",
            "とくべつ",
            "しゅうちゅう",
            "とくしゅう"
          ],
          "answer": "とっきゅう"
        }
      ]
    },
    {
      "type": "drills",
      "title": "Drill 2: Vocabulary",
      "instructions": "Choose the word that best completes each sentence.",
      "items": [
        {
          "kind": "mcq",
          "q": "テストの ______ を 書いて ください。",
          "choices": [
            "答え",
            "思い",
            "集中",
            "特急"
          ],
          "answer": "答え",
          "terms": [
            "v_tesuto",
            "p_no",
            "v_kotae",
            "p_wo",
            {
              "id": "v_kaku",
              "form": "te_form"
            },
            "v_kudasai"
          ]
        },
        {
          "kind": "mcq",
          "q": "今日は ______ 暑いです。",
          "choices": [
            "特に",
            "特急",
            "特集",
            "問答"
          ],
          "answer": "特に",
          "terms": [
            "v_kyou",
            "p_wa",
            "v_tokuni",
            {
              "id": "v_atsui",
              "form": "polite_adj"
            }
          ]
        },
        {
          "kind": "mcq",
          "q": "切手を ______ います。",
          "choices": [
            "集めて",
            "答えて",
            "思って",
            "集中して"
          ],
          "answer": "集めて",
          "terms": [
            "v_kitte",
            "p_wo",
            {
              "id": "v_atsumeru",
              "form": "te_form"
            },
            {
              "id": "v_iru",
              "form": "polite_masu"
            }
          ]
        },
        {
          "kind": "mcq",
          "q": "先生との ______ を 書きました。",
          "choices": [
            "思い出",
            "思い上がり",
            "思い",
            "意思"
          ],
          "answer": "思い出",
          "terms": [
            "v_sensei",
            "p_to",
            "p_no",
            "v_omoide",
            "p_wo",
            {
              "id": "v_kaku",
              "form": "polite_mashita"
            }
          ]
        },
        {
          "kind": "mcq",
          "q": "みんなが 集まる ______ が あります。",
          "choices": [
            "集会",
            "文集",
            "問答",
            "意思"
          ],
          "answer": "集会",
          "terms": [
            "v_minna",
            "p_ga",
            {
              "id": "v_atsumaru",
              "form": "plain_form"
            },
            "v_shuukai",
            "p_ga",
            {
              "id": "v_aru",
              "form": "polite_masu"
            }
          ]
        }
      ]
    },
    {
      "type": "drills",
      "title": "Drill 3: Grammar & Forms",
      "instructions": "Choose the correct grammar form to complete each sentence.",
      "items": [
        {
          "kind": "mcq",
          "q": "この 問題は むずかしいと ______。",
          "choices": [
            "思います",
            "集めます",
            "答えます",
            "集中します"
          ],
          "answer": "思います",
          "terms": [
            "v_kono",
            "v_mondai",
            "p_wa",
            "v_muzukashii",
            "p_to_quote",
            {
              "id": "v_omou",
              "form": "polite_masu"
            }
          ]
        },
        {
          "kind": "mcq",
          "q": "答えを 考えてから、先生に ______。",
          "choices": [
            "答えます",
            "集めます",
            "思います",
            "集まります"
          ],
          "answer": "答えます",
          "terms": [
            "v_kotae",
            "p_wo",
            {
              "id": "v_kangaeru",
              "form": "te_form"
            },
            "p_tekara",
            "v_sensei",
            "p_ni",
            {
              "id": "v_kotaeru",
              "form": "polite_masu"
            }
          ]
        },
        {
          "kind": "mcq",
          "q": "もっと 多くの 人が 集まれる ______ なると いいです。",
          "choices": [
            "ように",
            "ために",
            "ことが",
            "のに"
          ],
          "answer": "ように",
          "terms": [
            "v_motto",
            {
              "id": "v_ooi",
              "form": "adverbial"
            },
            "p_no",
            "v_hito",
            "p_ga",
            {
              "id": "v_atsumaru",
              "form": "potential"
            },
            "v_you_manner",
            "p_ni",
            {
              "id": "v_naru",
              "form": "plain_form"
            },
            "p_to_conditional",
            "v_ii"
          ]
        },
        {
          "kind": "mcq",
          "q": "試験の 前に、もっと 集中 ______。",
          "choices": [
            "しなければ いけません",
            "して います",
            "するように なりました",
            "してから 行きます"
          ],
          "answer": "しなければ いけません",
          "terms": [
            "v_shiken",
            "p_no",
            "v_mae",
            "p_ni",
            "v_motto",
            "v_shuuchuu",
            {
              "id": "v_suru",
              "form": "nakereba"
            },
            {
              "id": "v_ikeru",
              "form": "polite_negative"
            }
          ]
        }
      ]
    }
  ]
}